[
  {
    "language": "mojo",
    "path": "implementations/mojo",
    "metadata": {
      "language": "mojo",
      "version": "24.5",
      "author": "Mojo Implementation",
      "features": [
        "perft",
        "fen",
        "ai",
        "castling",
        "en_passant",
        "promotion"
      ],
      "max_ai_depth": 5,
      "estimated_perft4_ms": 1000,
      "build": "mojo build chess.mojo",
      "test": "mojo chess.mojo",
      "analyze": "mojo chess.mojo --no-run",
      "run": "mojo chess.mojo"
    },
    "track": "v2-full",
    "profile": "quick",
    "timings": {
      "image_build_seconds": 0.5103669166564941,
      "build_seconds": 10.073354244232178,
      "analyze_seconds": 10.05160665512085,
      "test_seconds": 10.04158878326416,
      "test_internal_seconds": 10.04158878326416,
      "test_chess_engine_seconds": 10.752640008926392,
      "test_v2_full_seconds": 10.752640008926392
    },
    "memory": {
      "image": {
        "memory_mb": 115.98046875,
        "peak_memory_mb": 115.98046875,
        "avg_memory_mb": 96.80546875,
        "avg_cpu_percent": 0.0,
        "samples": 5,
        "psutil_available": true
      },
      "build": {
        "memory_mb": 0,
        "peak_memory_mb": 0,
        "avg_cpu_percent": 0,
        "psutil_available": true,
        "source": "cgroup"
      },
      "analyze": {
        "memory_mb": 0,
        "peak_memory_mb": 0,
        "avg_cpu_percent": 0,
        "psutil_available": true,
        "source": "cgroup"
      },
      "test": {
        "memory_mb": 0,
        "peak_memory_mb": 0,
        "avg_cpu_percent": 0,
        "psutil_available": true,
        "source": "cgroup"
      },
      "test_chess_engine": {
        "memory_mb": 31.73046875,
        "peak_memory_mb": 61.69140625,
        "avg_memory_mb": 59.87302791262136,
        "avg_cpu_percent": 0.0,
        "samples": 103,
        "psutil_available": true
      }
    },
    "size": {
      "source_loc": 0,
      "source_files": 0
    },
    "normalized": {},
    "docker": {
      "build_time": 0.5103669166564941,
      "build_success": true,
      "image_build_time": 0.5103669166564941,
      "image_build_success": true,
      "make_build_skipped": false,
      "make_build_time": 10.073354244232178,
      "make_build_success": false,
      "make_analyze_time": 10.05160665512085,
      "make_analyze_success": false,
      "test_time": 10.04158878326416,
      "test_success": false,
      "make_test_time": 10.04158878326416,
      "make_test_success": false,
      "test_chess_engine_time": 10.752640008926392,
      "test_chess_engine_success": false,
      "track_test_time": 10.752640008926392,
      "track_test_success": false
    },
    "task_results": {
      "make_build": false,
      "make_analyze": false,
      "make_test": false,
      "make_test_chess_engine": false
    },
    "scores": {
      "make_test": {
        "passed": 0,
        "failed": 1,
        "total": 1
      },
      "make_test_chess_engine": {
        "passed": 0,
        "failed": 58,
        "errors": 42,
        "total": 58
      }
    },
    "test_results": {
      "passed": [],
      "failed": [
        "make_build",
        "make_analyze",
        "make_test",
        "make_test_chess_engine"
      ]
    },
    "errors": [
      "make build failed: 23:27:18.950 INFO: Metrics initialized.\nUsage: python -m max.entrypoints.pipelines serve [OPTIONS]\nTry 'python -m max.entrypoints.pipelines serve --help' for help.\n\nError: No such option: -c\n",
      "make analyze failed: 23:27:28.981 INFO: Metrics initialized.\nUsage: python -m max.entrypoints.pipelines serve [OPTIONS]\nTry 'python -m max.entrypoints.pipelines serve --help' for help.\n\nError: No such option: -c\n",
      "make test failed: 23:27:39.046 INFO: Metrics initialized.\nUsage: python -m max.entrypoints.pipelines serve [OPTIONS]\nTry 'python -m max.entrypoints.pipelines serve --help' for help.\n\nError: No such option: -c\n",
      "track v2-full suite failed: Found 1 implementation(s)\nLoaded 16 tests from test/suites/v2_full.json\n\nTesting mojo implementation at implementations/mojo\n----------------------------------------\nRunning test: Hash Command Baseline \u2717\nRunning test: Hash Command After Move \u2717\nRunning test: Draws Command \u2717\nRunning test: Go Movetime \u2717\nRunning test: PGN Show \u2717\nRunning test: PGN Fixture Morphy \u2717\nRunning test: PGN Fixture Byrne-Fischer \u2717\nRunning test: Book Load Stats \u2717\nRunning test: Book AI Move \u2717\nRunning test: UCI Handshake \u2717\nRunni"
    ],
    "status": "completed"
  }
]