[
  {
    "language": "php",
    "path": "implementations/php",
    "metadata": {
      "language": "php",
      "version": "8.3",
      "author": "PHP Implementation",
      "features": [
        "perft",
        "fen",
        "ai",
        "castling",
        "en_passant",
        "promotion"
      ],
      "max_ai_depth": 5,
      "estimated_perft4_ms": 1500,
      "benchmark.build": "skip",
      "build": "php -l chess.php",
      "test": "echo -e 'new\\nmove e2e4\\nmove e7e5\\nexport\\nquit' | php chess.php",
      "analyze": "find . -name '*.php' -exec php -l {} \\;",
      "run": "php chess.php"
    },
    "track": "v2-full",
    "profile": "quick",
    "timings": {
      "image_build_seconds": 0.2630598545074463,
      "build_seconds": null,
      "analyze_seconds": 0.3291294574737549,
      "test_seconds": 0.21445012092590332,
      "test_internal_seconds": 0.21445012092590332,
      "test_chess_engine_seconds": 9.948575973510742,
      "test_v2_full_seconds": 9.948575973510742
    },
    "memory": {
      "image": {
        "memory_mb": 114.12109375,
        "peak_memory_mb": 114.12109375,
        "avg_memory_mb": 84.80989583333333,
        "avg_cpu_percent": 0.0,
        "samples": 3,
        "psutil_available": true
      },
      "build": {
        "memory_mb": 0,
        "peak_memory_mb": 0,
        "avg_cpu_percent": 0,
        "psutil_available": true,
        "source": "skipped"
      },
      "analyze": {
        "memory_mb": 9.015625,
        "peak_memory_mb": 9.015625,
        "avg_cpu_percent": 0,
        "psutil_available": true,
        "source": "cgroup"
      },
      "test": {
        "memory_mb": 8.953125,
        "peak_memory_mb": 8.953125,
        "avg_cpu_percent": 0,
        "psutil_available": true,
        "source": "cgroup"
      },
      "test_chess_engine": {
        "memory_mb": 31.90234375,
        "peak_memory_mb": 61.7890625,
        "avg_memory_mb": 59.842203776041664,
        "avg_cpu_percent": 0.0,
        "samples": 96,
        "psutil_available": true
      }
    },
    "size": {
      "source_loc": 2936,
      "source_files": 10
    },
    "normalized": {
      "build_ms_per_kloc": 0.0,
      "analyze_ms_per_kloc": 112.10131385345875,
      "runtime_ms_per_kloc": 73.04159432081175
    },
    "docker": {
      "build_time": 0.2630598545074463,
      "build_success": true,
      "image_build_time": 0.2630598545074463,
      "image_build_success": true,
      "make_build_skipped": true,
      "make_build_time": null,
      "make_build_success": true,
      "make_analyze_time": 0.3291294574737549,
      "make_analyze_success": true,
      "test_time": 0.21445012092590332,
      "test_success": true,
      "make_test_time": 0.21445012092590332,
      "make_test_success": true,
      "test_chess_engine_time": 9.948575973510742,
      "test_chess_engine_success": true,
      "track_test_time": 9.948575973510742,
      "track_test_success": true
    },
    "task_results": {
      "make_build": true,
      "make_analyze": true,
      "make_test": true,
      "make_test_chess_engine": true
    },
    "scores": {
      "make_test": {
        "passed": 1,
        "failed": 0,
        "total": 1
      },
      "make_test_chess_engine": {
        "passed": 16,
        "failed": 0,
        "errors": 0,
        "total": 16
      }
    },
    "test_results": {
      "passed": [
        "make_build",
        "make_analyze",
        "make_test",
        "make_test_chess_engine"
      ],
      "failed": []
    },
    "errors": [],
    "status": "completed"
  }
]