[
  {
    "language": "rust",
    "path": "implementations/rust",
    "metadata": {
      "language": "rust",
      "version": "1.70",
      "author": "Rust Implementation",
      "features": [
        "perft",
        "fen",
        "ai",
        "castling",
        "en_passant",
        "promotion"
      ],
      "max_ai_depth": 5,
      "estimated_perft4_ms": 600,
      "build": "cargo build --release",
      "test": "cargo test",
      "analyze": "cargo check --all-targets",
      "run": "./target/release/chess"
    },
    "track": "v2-full",
    "profile": "full",
    "timings": {
      "image_build_seconds": 0.24463415145874023,
      "build_seconds": 0.19402408599853516,
      "analyze_seconds": 0.1989138126373291,
      "test_seconds": 0.17842388153076172,
      "test_internal_seconds": 0.17842388153076172,
      "test_chess_engine_seconds": 8.315528154373169,
      "test_v2_full_seconds": 8.315528154373169
    },
    "memory": {
      "image": {
        "memory_mb": 112.578125,
        "peak_memory_mb": 112.578125,
        "avg_memory_mb": 84.02604166666667,
        "avg_cpu_percent": 0.0,
        "samples": 3,
        "psutil_available": true
      },
      "build": {
        "memory_mb": 6.58984375,
        "peak_memory_mb": 6.58984375,
        "avg_cpu_percent": 0,
        "psutil_available": true,
        "source": "cgroup"
      },
      "analyze": {
        "memory_mb": 6.859375,
        "peak_memory_mb": 6.859375,
        "avg_cpu_percent": 0,
        "psutil_available": true,
        "source": "cgroup"
      },
      "test": {
        "memory_mb": 6.56640625,
        "peak_memory_mb": 6.56640625,
        "avg_cpu_percent": 0,
        "psutil_available": true,
        "source": "cgroup"
      },
      "test_chess_engine": {
        "memory_mb": 31.76953125,
        "peak_memory_mb": 61.7109375,
        "avg_memory_mb": 59.372998046875,
        "avg_cpu_percent": 0.0,
        "samples": 80,
        "psutil_available": true
      }
    },
    "size": {
      "source_loc": 1852,
      "source_files": 9
    },
    "normalized": {
      "build_ms_per_kloc": 104.76462526918745,
      "analyze_ms_per_kloc": 107.40486643484292,
      "runtime_ms_per_kloc": 96.3411887315128
    },
    "docker": {
      "build_time": 0.24463415145874023,
      "build_success": true,
      "image_build_time": 0.24463415145874023,
      "image_build_success": true,
      "make_build_skipped": false,
      "make_build_time": 0.19402408599853516,
      "make_build_success": true,
      "make_analyze_time": 0.1989138126373291,
      "make_analyze_success": true,
      "test_time": 0.17842388153076172,
      "test_success": true,
      "make_test_time": 0.17842388153076172,
      "make_test_success": true,
      "test_chess_engine_time": 8.315528154373169,
      "test_chess_engine_success": false,
      "track_test_time": 8.315528154373169,
      "track_test_success": false
    },
    "task_results": {
      "make_build": true,
      "make_analyze": true,
      "make_test": true,
      "make_test_chess_engine": false
    },
    "scores": {
      "make_test": {
        "passed": 1,
        "failed": 0,
        "total": 1
      },
      "make_test_chess_engine": {
        "passed": 2,
        "failed": 12,
        "errors": 0,
        "total": 14
      }
    },
    "test_results": {
      "passed": [],
      "failed": [
        "make_test_chess_engine"
      ]
    },
    "errors": [
      "track v2-full suite failed: Found 1 implementation(s)\nLoaded 14 tests from test/suites/v2_full.json\n\nTesting rust implementation at implementations/rust\n----------------------------------------\nRunning test: Hash Command Baseline \u2713\nRunning test: Hash Command After Move \u2713\nRunning test: Draws Command \u2717\nRunning test: Go Movetime \u2717\nRunning test: PGN Show \u2717\nRunning test: PGN Fixture Morphy \u2717\nRunning test: PGN Fixture Byrne-Fischer \u2717\nRunning test: UCI Handshake \u2717\nRunning test: UCI Fixture Handshake \u2717\nRunning test: New960 Positio"
    ],
    "status": "completed"
  }
]